README.md
setup.py
PETvisualizer/Colors.py
PETvisualizer/CreateProcessGraph.py
PETvisualizer/Labels.py
PETvisualizer/PETVisualizer.py
PETvisualizer/ShowProcessGraph.py
PETvisualizer/__init__.py
PETvisualizer/main.py
PETvisualizer/pet-entities.json
PETvisualizer/pet-relations.json
PETvisualizer/utility.py
PETvisualizer/wolfgold.png
petannotationvisualizer.egg-info/PKG-INFO
petannotationvisualizer.egg-info/SOURCES.txt
petannotationvisualizer.egg-info/dependency_links.txt
petannotationvisualizer.egg-info/requires.txt
petannotationvisualizer.egg-info/top_level.txt